scrapenewsapi/__init__.py
scrapenewsapi/config/__init__.py
scrapenewsapi/config/auth.py
scrapenewsapi/config/constants.py
scrapenewsapi/config/setup.py
scrapenewsapi/src/__init__.py
scrapenewsapi/src/main.py
scrapenewsapi/src/queries.py
newsapi_scraper-0.0.1.dist-info/LICENSE.txt
newsapi_scraper-0.0.1.dist-info/METADATA
newsapi_scraper-0.0.1.dist-info/WHEEL
newsapi_scraper-0.0.1.dist-info/top_level.txt
newsapi_scraper-0.0.1.dist-info/RECORD
