Metadata-Version: 2.1
Name: newsapi-scraper
Version: 0.0.1
Summary: A fork of the newsapi-python repo. Intended to clean up the code for personal use.
Home-page: UNKNOWN
Author: Kirtus Justus
Author-email: kirtusjustus@outlook.com
License: UNKNOWN
Keywords: newsapi,news
Platform: UNKNOWN
Classifier: Programming Language :: Python :: 3
Classifier: License :: OSI Approved :: MIT License
Classifier: Operating System :: OS Independent
Requires-Dist: requests (==2.21.0)
